<?xml version='1.0' encoding='utf-8' ?>
<!DOCTYPE appendix PUBLIC "-//OASIS//DTD DocBook XML V4.5//EN" "http://www.oasis-open.org/docbook/xml/4.5/docbookx.dtd" [
]>
<appendix id="appe-DEC_Guide-Revision_History">
  <title>Revision History</title>
  <simpara>
    <revhistory>
      <revision>
	<revnumber>3</revnumber>
	<date>Tue Feb 23 2010</date>
	<author>
	  <firstname>John</firstname>
	  <surname>McDonough</surname>
	  <email>wb8rcr@arrl.net</email>
	</author>
	<revdescription>
	  <simplelist>
	    <member>Use tables instead of segmentedlist to make pdf work better</member>
	  </simplelist>
	</revdescription>
      </revision>
      <revision>
	<revnumber>2</revnumber>
	<date>Mon Feb 22 2010</date>
	<author>
	  <firstname>John</firstname>
	  <surname>McDonough</surname>
	  <email>wb8rcr@arrl.net</email>
	</author>
	<revdescription>
	  <simplelist>
	    <member>Add Objectives</member>
	    <member>Add Other</member>
	    <member>Rearrange sections</member>
	  </simplelist>
	</revdescription>
      </revision>
      <revision>
	<revnumber>1</revnumber>
	<date>Wed Feb 10 2010</date>
	<author>
	  <firstname>John</firstname>
	  <surname>McDonough</surname>
	  <email>wb8rcr@arrl.net</email>
	</author>
	<revdescription>
	  <simplelist>
	    <member>Additional content</member>
	    <member>Test admonitions</member>
	  </simplelist>
	</revdescription>
      </revision>
      <revision>
	<revnumber>0</revnumber>
	<date>Tue Feb 9 2010</date>
	<author>
	  <firstname>John</firstname>
	  <surname>McDonough</surname>
	  <email>wb8rcr@arrl.net</email>
	</author>
	<revdescription>
	  <simplelist>
	    <member>Initial creation of book by publican</member>
	  </simplelist>
	</revdescription>
      </revision>
    </revhistory>
  </simpara>
</appendix>

